setup.py
tornadoutil.py
tornado_logging_app.egg-info/PKG-INFO
tornado_logging_app.egg-info/SOURCES.txt
tornado_logging_app.egg-info/dependency_links.txt
tornado_logging_app.egg-info/requires.txt
tornado_logging_app.egg-info/top_level.txt
tornado_logging_app.egg-info/zip-safe