Metadata-Version: 1.0
Name: tornado-logging-app
Version: 0.1
Summary: Base logging tornado app
Home-page: https://github.com/langloisjp/tornado-logging-app
Author: Jean-Philippe Langlois
Author-email: jpl@jplanglois.com
License: MIT
Platform: UNKNOWN
